logger/__init__.py
logger/logger.py
ems_simple_logger_config-0.0.3.dist-info/LICENSE
ems_simple_logger_config-0.0.3.dist-info/METADATA
ems_simple_logger_config-0.0.3.dist-info/WHEEL
ems_simple_logger_config-0.0.3.dist-info/top_level.txt
ems_simple_logger_config-0.0.3.dist-info/RECORD
