Metadata-Version: 2.1
Name: ems-simple-logger-config
Version: 0.0.3
Summary: A simple file logger configuration for Python
Home-page: https://github.com/xemage/ems-simple-logger-config
Author: xemage
License: UNKNOWN
Project-URL: Bug Tracker, https://github.com/xemage/ems-simple-logger-config/issues
Platform: UNKNOWN
Classifier: Programming Language :: Python :: 3
Classifier: License :: OSI Approved :: MIT License
Classifier: Operating System :: OS Independent
Requires-Python: >=3.8
License-File: LICENSE
